{
  "configVersion": 1,
  "timestamp": 1684841710629,
  "index": "https://web-cdttu.github.io/index.html",
  "assetGroups": [
    {
      "name": "app",
      "installMode": "prefetch",
      "updateMode": "prefetch",
      "cacheQueryOptions": {
        "ignoreVary": true
      },
      "urls": [
        "https://web-cdttu.github.io/249.70488cc8980beffb.js",
        "https://web-cdttu.github.io/820.fda63ba82344096c.js",
        "https://web-cdttu.github.io/favicon.ico",
        "https://web-cdttu.github.io/index.html",
        "https://web-cdttu.github.io/main.b24930dcaf62fce1.js",
        "https://web-cdttu.github.io/manifest.webmanifest",
        "https://web-cdttu.github.io/polyfills.b51b8edc601a6e74.js",
        "https://web-cdttu.github.io/runtime.a220d7aa967e36a3.js",
        "https://web-cdttu.github.io/styles.1f90d279df412801.css"
      ],
      "patterns": []
    },
    {
      "name": "assets",
      "installMode": "lazy",
      "updateMode": "prefetch",
      "cacheQueryOptions": {
        "ignoreVary": true
      },
      "urls": [
        "https://web-cdttu.github.io/assets/icons/icon-192x192.png",
        "https://web-cdttu.github.io/assets/icons/icon-256x256.png",
        "https://web-cdttu.github.io/assets/icons/icon-384x384.png",
        "https://web-cdttu.github.io/assets/icons/icon-512x512.png",
        "https://web-cdttu.github.io/assets/images/header-background.png"
      ],
      "patterns": []
    }
  ],
  "dataGroups": [],
  "hashTable": {
    "https://web-cdttu.github.io/249.70488cc8980beffb.js": "3665adc03fecd6c9ff9941b9362dcefb845e1cc2",
    "https://web-cdttu.github.io/820.fda63ba82344096c.js": "d02006deb0ddcd47382c69eed7ea6edd4657750b",
    "https://web-cdttu.github.io/assets/icons/icon-192x192.png": "6c28d04e8c85897db44353d12deef1035edbba6e",
    "https://web-cdttu.github.io/assets/icons/icon-256x256.png": "bc7ccf676e025fc6c353b3d2c2ec6d06a6eed3be",
    "https://web-cdttu.github.io/assets/icons/icon-384x384.png": "dac524faf2b05ec8f9309931f7194fb5f97e06f6",
    "https://web-cdttu.github.io/assets/icons/icon-512x512.png": "946081eea5b25aec0e6942d07091664904529ac1",
    "https://web-cdttu.github.io/assets/images/header-background.png": "9449c1968fce606e4db5231a29828ff3c58784e6",
    "https://web-cdttu.github.io/favicon.ico": "b125295a96e45af33b6a7f4169425b51d992c5f6",
    "https://web-cdttu.github.io/index.html": "b4cf4d9e136035f740fd0fe479cc47e1f3072bb7",
    "https://web-cdttu.github.io/main.b24930dcaf62fce1.js": "0e2b52c52758ca437aee58e4b067df321384d671",
    "https://web-cdttu.github.io/manifest.webmanifest": "e45a0df9578af7cd77b7d8df0c628b85e014e7a0",
    "https://web-cdttu.github.io/polyfills.b51b8edc601a6e74.js": "eeb3f3c1d4c9bb3b75b2aadb368be7bd21bfa312",
    "https://web-cdttu.github.io/runtime.a220d7aa967e36a3.js": "500acf3fe544e839d31ab7baf97b2f8686e53381",
    "https://web-cdttu.github.io/styles.1f90d279df412801.css": "b3077ddeb2e53c05b74c8088cef07dbe8db422c2"
  },
  "navigationUrls": [
    {
      "positive": true,
      "regex": "^\\/.*$"
    },
    {
      "positive": false,
      "regex": "^\\/(?:.+\\/)?[^/]*\\.[^/]*$"
    },
    {
      "positive": false,
      "regex": "^\\/(?:.+\\/)?[^/]*__[^/]*$"
    },
    {
      "positive": false,
      "regex": "^\\/(?:.+\\/)?[^/]*__[^/]*\\/.*$"
    }
  ],
  "navigationRequestStrategy": "performance"
}